npc_io/__init__.py
npc_io/cached_property.py
npc_io/file_io.py
npc_io/lazy_dict.py
npc_io/py.typed
npc_io/types.py
npc_io-0.1.32.dist-info/LICENSE
npc_io-0.1.32.dist-info/METADATA
npc_io-0.1.32.dist-info/WHEEL
npc_io-0.1.32.dist-info/top_level.txt
npc_io-0.1.32.dist-info/RECORD
