Metadata-Version: 2.1
Name: npc-io
Version: 0.1.32
Summary: File IO tools for MindScope Neuropixels projects in the cloud.
Author-email: Ben Hardcastle <ben.hardcastle@alleninstitue.org>
License: MIT
Project-URL: Repository, https://github.com/AllenInstitute/npc_io
Project-URL: Issues, https://github.com/AllenInstitute/npc_io/issues
Classifier: Development Status :: 3 - Alpha
Classifier: Programming Language :: Python :: 3
Classifier: Programming Language :: Python :: 3.9
Classifier: Programming Language :: Python :: 3.10
Classifier: Programming Language :: Python :: 3.11
Classifier: License :: OSI Approved :: MIT License
Classifier: Operating System :: Microsoft :: Windows
Classifier: Operating System :: POSIX :: Linux
Requires-Python: >=3.9
License-File: LICENSE
Requires-Dist: crc32c>=2.3.post0
Requires-Dist: universal-pathlib<0.2.0
Requires-Dist: typing-extensions>=4.9.0
Requires-Dist: python-dotenv>=1.0.1
Requires-Dist: s3fs>=2023.12.2
Requires-Dist: boto3==1.28.17
